inferencesh/__init__.py
inferencesh/agent.py
inferencesh/client.py
inferencesh/tools.py
inferencesh/types.py
inferencesh/api/__init__.py
inferencesh/api/agents.py
inferencesh/api/files.py
inferencesh/api/tasks.py
inferencesh/models/__init__.py
inferencesh/models/base.py
inferencesh/models/errors.py
inferencesh/models/file.py
inferencesh/models/llm.py
inferencesh/models/output_meta.py
inferencesh/utils/__init__.py
inferencesh/utils/download.py
inferencesh/utils/storage.py
inferencesh-0.6.9.dist-info/licenses/LICENSE
inferencesh-0.6.9.dist-info/METADATA
inferencesh-0.6.9.dist-info/WHEEL
inferencesh-0.6.9.dist-info/entry_points.txt
inferencesh-0.6.9.dist-info/top_level.txt
inferencesh-0.6.9.dist-info/RECORD
