Metadata-Version: 2.4
Name: inferencesh
Version: 0.6.9
Summary: inference.sh Python SDK
Author-email: "Inference Shell Inc." <hello@inference.sh>
Project-URL: Homepage, https://github.com/inference-sh/sdk
Project-URL: Bug Tracker, https://github.com/inference-sh/sdk/issues
Classifier: Programming Language :: Python :: 3
Classifier: License :: OSI Approved :: MIT License
Classifier: Operating System :: OS Independent
Requires-Python: >=3.7
License-File: LICENSE
Requires-Dist: pydantic>=2.0.0
Requires-Dist: tqdm>=4.67.0
Requires-Dist: requests>=2.31.0
Provides-Extra: test
Requires-Dist: pytest>=7.0.0; extra == "test"
Requires-Dist: pytest-cov>=4.0.0; extra == "test"
Provides-Extra: async
Requires-Dist: aiohttp>=3.9.0; python_version >= "3.8" and extra == "async"
Requires-Dist: aiofiles>=23.2.1; python_version >= "3.8" and extra == "async"
Dynamic: license-file
